tedsverysimplemodule/__init__.py
tedsverysimplemodule/add.py
tedsverysimplemodule/subtract.py
tedsverysimplemodule/extras/__init__.py
tedsverysimplemodule/extras/divide.py
tedsverysimplemodule/extras/multiply.py
verysimplemodule/__init__.py
verysimplemodule/add.py
verysimplemodule/subtract.py
verysimplemodule/extras/__init__.py
verysimplemodule/extras/divide.py
verysimplemodule/extras/multiply.py
tedsverysimplemodule-0.0.1.dist-info/METADATA
tedsverysimplemodule-0.0.1.dist-info/WHEEL
tedsverysimplemodule-0.0.1.dist-info/top_level.txt
tedsverysimplemodule-0.0.1.dist-info/RECORD
